CHANGES
LICENSE
MANIFEST.in
Makefile
README.md
setup.py
scratch/__init__.py
scratch/scratch.py
scratchpy.egg-info/PKG-INFO
scratchpy.egg-info/SOURCES.txt
scratchpy.egg-info/dependency_links.txt
scratchpy.egg-info/not-zip-safe
scratchpy.egg-info/top_level.txt
tests/__init__.py
tests/parsing.py