Metadata-Version: 1.0
Name: scratchpy
Version: 0.1.0
Summary: A Python interface to Scratch
Home-page: http://github.com/pilliq/scratchpy
Author: Phillip Quiza
Author-email: pquiza@gmail.com
License: MIT
Keywords: Scratch
Platform: UNKNOWN
